Workbook

Sheet Table Of Contents
D3: Restro Order Reports
D6: Thursday, March 21, 2024
D9: Table Of Contents
D10: Summary
D12: Daily Purchase Report
D14: Daily Sales Report
D16: Card Transactions
D18: Cheque Transactions
D20: Daily Stock Report
D22: Customer Balance
D24: Vendor Balance

Sheet Summary
D3: Daily Summary Report
D6: ='Table Of Contents'!$D$6:$L$6 -> #VALUE!
D9: Opening Balance | E9: 112794 | G9: Cash Denomination | H9: Qty. | L9: Bank | M9: Amount | O9: Cost Center | P9: Sales
C10: Sales | D10: Cash | E10: 495 | G10: 1000 | H10: 0 | I10: =H10*G10 -> 0 | O10: Bar | P10: 438.05
D11: Card | E11: 0 | G11: 500 | H11: 0 | I11: =H11*G11 -> 0
D12: Cheque | E12: 0 | G12: 100 | H12: 0 | I12: =H12*G12 -> 0
D13: Credit | E13: 0 | G13: 50 | H13: 0 | I13: =H13*G13 -> 0
D14: eSewa | E14: 0 | G14: 20 | H14: 0 | I14: =H14*G14 -> 0
D15: FonePay | E15: 0 | G15: 10 | H15: 0 | I15: =H15*G15 -> 0
D16: Surplus/Deficit | E16: 0 | G16: 5 | H16: 0 | I16: =H16*G16 -> 0
C17: Credit | D17: Cash | E17: 0 | G17: 2 | H17: 0 | I17: =H17*G17 -> 0
D18: Card | E18: 0 | G18: 1 | H18: 113289 | I18: =H18*G16 -> 566445
D19: Cheque | E19: 0 | I19: =H19*G17 -> 0
D20: eSewa | E20: 0 | I20: =H20*G18 -> 0
D21: FonePay | E21: 0 | G21: Total | I21: =SUM(I10:I20) -> 566445
C22: Advance | D22: Cash | E22: 0
D23: Card | E23: 0
D24: Cheque | E24: 0
D25: eSewa | E25: 0
D26: FonePay | E26: 0
D27: Total Cash Received | E27: 495
D28: Total Expenses | E28: 0
D29: Cash In Counter | E29: 113289
D30: Cash Settlement | E30: 0
D31: Closing Balance | E31: 113289

Sheet Daily Purchase Report
D3: Daily Purchase Report
D6: ='Table Of Contents'!$D$6:$L$6 -> #VALUE!
D9: SN | E9: PurchaseNo. | F9: Vender | G9: Address | H9: Item Name | I9: Qty | J9: Unit | K9: Rate(Rs.) | L9: VAT(Rs.) | M9: Amount(Rs.) | N9: Fiscal Year | O9: PurchaseBy | P9: Date

Sheet Daily Sales Report
D3: Daily Sales Report
D6: ='Table Of Contents'!$D$6:$L$6 -> #VALUE!
D9: Bill No | E9: Time | F9: Basic Amnt | G9: Discount | H9: Srv. Chrg | I9: VAT | J9: Net Amt | K9: Tender Amt | L9: Return Amt | M9: Received Amt | N9: Cheque Amt | O9: Card Amt | P9: Credit Amt | Q9: Payment Mode | R9: Customer
D10: RO80/81-331 | E10: 11:18:25 | F10: 438.05 | G10: 0 | H10: 0 | I10: 56.95 | J10: 495 | K10: 495 | L10: 0 | M10: 495 | N10: 0 | O10: 0 | P10: 0 | Q10: CASH
D11: Total | F11: =SUM(F10:F10) -> 438.05 | G11: =SUM(G10:G10) -> 0 | H11: =SUM(H10:H10) -> 0 | I11: =SUM(I10:I10) -> 56.95 | J11: =SUM(J10:J10) -> 495 | K11: =SUM(K10:K10) -> 495 | L11: =SUM(L10:L10) -> 0 | M11: =SUM(M10:M10) -> 495 | ... P11: =SUM(P10:P10) -> 0 | T11: Breakfast(<12 PM) | W11: Lunch(12 PM To 4 PM)
T12: Sales Amount | U12: 438.05 | W12: Sales Amount | X12: 0
T13: Discount | U13: 0 | W13: Discount | X13: 0
T14: S.Charge | U14: 0 | W14: S.Charge | X14: 0
T15: VAT | U15: 56.95 | W15: VAT | X15: 0
T16: Total Lunch Sales | U16: =U12-U13+U14+U15 -> 495 | W16: Total Ala Carte Sales | X16: =X12-X13+X14+X15 -> 0
T18: Dinner(>4 PM) | W18: Total Sales
T19: Sales Amount | U19: 0 | W19: Sales Amount | X19: 438.05
T20: Discount | U20: 0 | W20: Discount | X20: 0
T21: S.Charge | U21: 0 | W21: S.Charge | X21: 0
T22: VAT | U22: 0 | W22: VAT | X22: 56.95
T23: Total Party Sales | U23: =U19-U20+U21+U22 -> 0 | W23: Total | X23: =X19+X20+X21+X22 -> 495

Sheet Card Transactions
D3: Card Sales Report
D6: ='Table Of Contents'!$D$6:$L$6 -> #VALUE!
D9: Bill Date | E9: Bill No | F9: Room | G9: Table | H9: Provider | I9: Pay Mode | J9: Check # | K9: Transcation # | L9: Amount

Sheet Cheque Transactions
D3: Cheque Sales Report
D6: ='Table Of Contents'!$D$6:$L$6 -> #VALUE!
D9: Bill Date | E9: Bill No | F9: Room | G9: Table | H9: Provider | I9: Pay Mode | J9: Check # | K9: Transcation # | L9: Amount

Sheet Credit Collection
D3: Cheque Sales Report
D6: ='Table Of Contents'!$D$6:$L$6 -> #VALUE!
D9: Date | E9: Customer | F9: Payment Mode | G9: Amount | H9: Received By

Sheet Daily Stock Report
D3: Daily Stock Report
D6: ='Table Of Contents'!$D$6:$L$6 -> #VALUE!
D9: ItemName | E9: Opening Balance | F9: Purchase | G9: Consumed | H9: Closing Balance | I9: Unit
D10: Cfc | E10: 0 | F10: 0 | G10: 0 | H10: 0 | I10: pcs
D11: hot wings | E11: 0 | F11: 0 | G11: 0 | H11: 0 | I11: gm
D12: Crunchy Chicken Patty | E12: 0 | F12: 0 | G12: 0 | H12: 0 | I12: gm
D13: PopCorn | E13: 0 | F13: 0 | G13: 0 | H13: 0 | I13: gm
D14: Buff Sausage | E14: 0 | F14: 0 | G14: 0 | H14: 0 | I14: pcs
D15: Chicken Sausage | E15: 0 | F15: 0 | G15: 0 | H15: 0 | I15: pcs
D16: Chicken ball | E16: 0 | F16: 0 | G16: 0 | H16: 0 | I16: gm
D17: Grill Chicken Patty | E17: 0 | F17: 0 | G17: 0 | H17: 0 | I17: pcs
D18: Grill Ham Patty | E18: 0 | F18: 0 | G18: 0 | H18: 0 | I18: pcs
D19: Grill veg patty | E19: 0 | F19: 0 | G19: 0 | H19: 0 | I19: pcs
D20: MicroGreen | E20: 0 | F20: 0 | G20: 0 | H20: 0 | I20: pcs
D21: Burger bun | E21: 0 | F21: 0 | G21: 0 | H21: 0 | I21: pcs
... D288: deepa | E288: 0 | F288: 0 | G288: 0 | H288: 0 | I288: gm

Sheet Customers
D3: Customer Balance
D6: ='Table Of Contents'!$D$6:$L$6 -> #VALUE!
D9: Full Name | E9: Country | F9: City | G9: Address | H9: Contact No | I9: Card Number | J9: PAN | K9: Credit Balance
D10: Ajesh Tamrakar | E10: nepal | F10: Bhaktapur | G10: Bhaktapur | H10: 9801050009 | K10: 12.00
D11: Anjana Waiter | G11: salaghari | H11: 9808527299 | K11: 1548.00
D12: Binod Waiter | H12: 9808527299 | K12: 500.00
D13: Cosmetic Shop | E13: nepal | F13: Bhaktapur | G13: Radhe Rahde | H13: 9843123456 | K13: 12.00
D14: Dilip Kutu | E14: nepal | G14: Kausaltar | H14: 9808527299 | K14: -10486.00
D15: Yawahang Rai | E15: Nepal | F15: Kathmandu | G15: Pepsicola | H15: 9849138899 | I15: 1111111111 | J15: 12121 | K15: 2.00

Sheet Vendors
D3: Vendor Balance
D6: ='Table Of Contents'!$D$6:$L$6 -> #VALUE!
D9: Full Name | E9: Country | F9: City | G9: Address | H9: Contact No | I9: Card Number | J9: PAN | K9: Credit Balance
