Workbook

Sheet Table Of Contents
B1: RestroOrder Reports
D3: Table Of Contents
D6: Sunday, December 11, 2016
D9: # | E9: Report | F9: Description
D10: 1 | E10: =HYPERLINK("#'Summary'!A1","Summary") -> Summary | F10: Financial overview and cash breakdown
D11: 2 | E11: =HYPERLINK("#'Daily Purchase Report'!A1","Daily Purchase Report") -> Daily Purchase Report | F11: Purchases made during the day
D12: 3 | E12: =HYPERLINK("#'Daily Sales Report'!A1","Daily Sales Report") -> Daily Sales Report | F12: Bill-by-bill sales with payment breakdown
D13: 4 | E13: =HYPERLINK("#'Item Sales Report'!A1","Item Sales Report") -> Item Sales Report | F13: Sales grouped by category and item
D14: 5 | E14: =HYPERLINK("#'Card Transactions'!A1","Card Transactions") -> Card Transactions | F14: All card payment transactions
D15: 6 | E15: =HYPERLINK("#'Cheque Transactions'!A1","Cheque Transactions") -> Cheque Transactions | F15: All cheque payment transactions
D16: 7 | E16: =HYPERLINK("#'Credit Collection'!A1","Credit Collection") -> Credit Collection | F16: Credit payments collected
D17: 8 | E17: =HYPERLINK("#'Daily Stock Report'!A1","Daily Stock Report") -> Daily Stock Report | F17: Opening, consumed and closing stock
D18: 9 | E18: =HYPERLINK("#'Customers'!A1","Customers") -> Customers | F18: Customer credit balances
D19: 10 | E19: =HYPERLINK("#'Vendors'!A1","Vendors") -> Vendors | F19: Vendor balances

Sheet Summary
A1: Back to TOC | B1: RestroOrder Reports
D3: Daily Summary Report
D6: ='Table Of Contents'!$D$6 -> Sunday, December 11, 2016
D9: Opening Balance | G9: Cash Denomination | H9: Qty | I9: Total | K9: Provider | L9: Amount (Rs.) | N9: Cost Center | O9: Sales (Rs.)
D10: Sales | E10: Cash | G10: 1000 | I10: =G10*H10 -> 0
E11: Card | G11: 500 | I11: =G11*H11 -> 0
E12: Cheque | G12: 100 | I12: =G12*H12 -> 0
E13: Credit | G13: 50 | I13: =G13*H13 -> 0
E14: eSewa | G14: 20 | I14: =G14*H14 -> 0
E15: FonePay | G15: 10 | I15: =G15*H15 -> 0
E16: Surplus/Deficit | G16: 5 | I16: =G16*H16 -> 0
D17: Credit | E17: Cash | G17: 2 | I17: =G17*H17 -> 0
E18: Card | G18: 1 | I18: =G18*H18 -> 0
E19: Cheque | G19: Total | I19: =SUM(I10:I18) -> 0
E20: eSewa
E21: FonePay
D22: Advance | E22: Cash
E23: Card
E24: Cheque
E25: eSewa
E26: FonePay
D27: Total Cash Received
D28: Total Expenses
D29: Cash In Counter
D30: Cash Settlement
D31: Closing Balance

Sheet Daily Purchase Report
A1: Back to TOC | B1: RestroOrder Reports
D3: Daily Purchase Report
D6: ='Table Of Contents'!$D$6 -> Sunday, December 11, 2016
D9: SN | E9: Purchase No. | F9: Vendor | G9: Address | H9: Item Name | I9: Qty | J9: Unit | K9: Rate (Rs.) | L9: VAT (Rs.) | M9: Amount (Rs.) | N9: Fiscal Year | O9: Purchased By | P9: Date

Sheet Daily Sales Report
A1: Back to TOC | B1: RestroOrder Reports
D3: Daily Sales Report
D6: ='Table Of Contents'!$D$6 -> Sunday, December 11, 2016
D9: Bill No | E9: Time | F9: Basic Amt | G9: Discount | H9: Srv. Charge | I9: VAT | J9: Net Amt | K9: Tender Amt | L9: Return Amt | M9: Received Amt | N9: Cheque Amt | O9: Card Amt | P9: Credit Amt | Q9: Payment Mode | R9: Customer
T11: Breakfast (< 12 PM) | W11: Lunch (12–4 PM)
T12: Sales Amount | W12: Sales Amount
T13: Discount | W13: Discount
T14: S. Charge | W14: S. Charge
T15: VAT | W15: VAT
T16: Breakfast Total | W16: Lunch Total
T18: Dinner (> 4 PM) | W18: Grand Total
T19: Sales Amount | W19: Sales Amount
T20: Discount | W20: Discount
T21: S. Charge | W21: S. Charge
T22: VAT | W22: VAT
T23: Dinner Total | W23: Grand Total

Sheet Card Transactions
A1: Back to TOC | B1: RestroOrder Reports
D3: Card Transactions
D6: ='Table Of Contents'!$D$6 -> Sunday, December 11, 2016
D9: Bill Date | E9: Bill No | F9: Room | G9: Table | H9: Provider | I9: Pay Mode | J9: Check # | K9: Transaction # | L9: Amount (Rs.)

Sheet Cheque Transactions
A1: Back to TOC | B1: RestroOrder Reports
D3: Cheque Transactions
D6: ='Table Of Contents'!$D$6 -> Sunday, December 11, 2016
D9: Bill Date | E9: Bill No | F9: Room | G9: Table | H9: Provider | I9: Pay Mode | J9: Check # | K9: Transaction # | L9: Amount (Rs.)

Sheet Credit Collection
A1: Back to TOC | B1: RestroOrder Reports
D3: Credit Collection
D6: ='Table Of Contents'!$D$6 -> Sunday, December 11, 2016
D9: Date | E9: Customer | F9: Payment Mode | G9: Amount (Rs.) | H9: Received By

Sheet Daily Stock Report
A1: Back to TOC | B1: RestroOrder Reports
D3: Daily Stock Report
D6: ='Table Of Contents'!$D$6 -> Sunday, December 11, 2016
D9: Item Name | E9: Opening Balance | F9: Purchase | G9: Consumed | H9: Closing Balance | I9: Unit

Sheet Customers
A1: Back to TOC | B1: RestroOrder Reports
D3: Customers
D6: ='Table Of Contents'!$D$6 -> Sunday, December 11, 2016
D9: Full Name | E9: Country | F9: City | G9: Address | H9: Contact No. | I9: Card Number | J9: PAN | K9: Credit Balance

Sheet Vendors
A1: Back to TOC | B1: RestroOrder Reports
D3: Vendors
D6: ='Table Of Contents'!$D$6 -> Sunday, December 11, 2016
D9: Full Name | E9: Country | F9: City | G9: Address | H9: Contact No. | I9: Card Number | J9: PAN | K9: Credit Balance

Sheet Item Sales Report
A1: Back to TOC | B1: RestroOrder Reports
D3: Item Sales Report
D6: ='Table Of Contents'!$D$6 -> Sunday, December 11, 2016
D9: Category | E9: Item Name | F9: Qty | G9: Unit | H9: Unit Price (Rs.) | I9: Net Amount (Rs.)
